iepy/__init__.py
iepy/defaults.py
iepy/metrics.py
iepy/utils.py
iepy/version.txt
iepy/data/__init__.py
iepy/data/db.py
iepy/data/models.py
iepy/data/output.py
iepy/extraction/__init__.py
iepy/extraction/active_learning_core.py
iepy/extraction/features.py
iepy/extraction/relation_extraction_classifier.py
iepy/extraction/rules.py
iepy/extraction/rules_core.py
iepy/extraction/terminal.py
iepy/instantiation/__init__.py
iepy/instantiation/command_line.py
iepy/instantiation/csv_to_iepy.py
iepy/instantiation/gazettes_loader.py
iepy/instantiation/iepy_rules_runner.py
iepy/instantiation/iepy_runner.py
iepy/instantiation/instance_admin.py
iepy/instantiation/manage.py
iepy/instantiation/preprocess.py
iepy/instantiation/rules_verifier.py
iepy/instantiation/settings.py.template
iepy/preprocess/__init__.py
iepy/preprocess/corenlp.py
iepy/preprocess/pipeline.py
iepy/preprocess/segmenter.py
iepy/preprocess/stanford_preprocess.py
iepy/preprocess/tagger.py
iepy/preprocess/tokenizer.py
iepy/preprocess/ner/__init__.py
iepy/preprocess/ner/base.py
iepy/preprocess/ner/combiner.py
iepy/preprocess/ner/literal.py
iepy/preprocess/ner/stanford.py
iepy/preprocess/utils/get-java-version.jar
iepy/webui/__init__.py
iepy/webui/manage.py
iepy/webui/corpus/__init__.py
iepy/webui/corpus/admin.py
iepy/webui/corpus/api.py
iepy/webui/corpus/fields.py
iepy/webui/corpus/forms.py
iepy/webui/corpus/models.py
iepy/webui/corpus/serializer.py
iepy/webui/corpus/signals.py
iepy/webui/corpus/tests.py
iepy/webui/corpus/urls.py
iepy/webui/corpus/views.py
iepy/webui/corpus/migrations/0001_initial.py
iepy/webui/corpus/migrations/0001_squashed_0014_remove_segmenttotag_run_number.py
iepy/webui/corpus/migrations/0002_auto_20140918_1733.py
iepy/webui/corpus/migrations/0002_data_migration_dont_know_skip_merge.py
iepy/webui/corpus/migrations/0003_auto_20140922_1547.py
iepy/webui/corpus/migrations/0003_remove_dont_know_option.py
iepy-0.9.5.dist-info/DESCRIPTION.rst
iepy-0.9.5.dist-info/METADATA
iepy-0.9.5.dist-info/RECORD
iepy-0.9.5.dist-info/WHEEL
iepy-0.9.5.dist-info/entry_points.txt
iepy-0.9.5.dist-info/metadata.json
iepy-0.9.5.dist-info/top_level.txt
