Metadata-Version: 2.0
Name: iepy
Version: 0.9.5
Summary: Information Extraction framework in Python
Home-page: https://github.com/machinalis/iepy
Author: Rafael Carrascosa, Javier Mansilla, Gonzalo García Berrotarán, Daniel Moisset, Franco M. Luque
Author-email: UNKNOWN
License: BSD
Keywords: information extraction relation detection
Platform: UNKNOWN
Classifier: Development Status :: 5 - Production/Stable
Classifier: Intended Audience :: Developers
Classifier: Intended Audience :: Science/Research
Classifier: Intended Audience :: Information Technology
Classifier: License :: OSI Approved :: BSD License
Classifier: Programming Language :: Python :: 3
Classifier: Programming Language :: Python :: 3.2
Classifier: Programming Language :: Python :: 3.3
Classifier: Programming Language :: Python :: 3.4
Classifier: Programming Language :: Python :: 3 :: Only
Requires-Dist: Django (==1.7.6)
Requires-Dist: REfO (==0.13)
Requires-Dist: appdirs (==1.2.0)
Requires-Dist: colorama (==0.2.7)
Requires-Dist: django-angular (==0.7.8)
Requires-Dist: django-extra-views (==0.7.1)
Requires-Dist: django-relatedadminwidget (==0.0.3)
Requires-Dist: django-relatives (==0.3.1)
Requires-Dist: docopt (==0.6.1)
Requires-Dist: factory-boy (==2.4.1)
Requires-Dist: featureforge (>=0.1.5)
Requires-Dist: future (==0.11.4)
Requires-Dist: jsonfield (==1.0.0)
Requires-Dist: nltk (==3.0.0)
Requires-Dist: nose (==1.3.0)
Requires-Dist: numpy (>=1.8.0)
Requires-Dist: scikit-learn (==0.15.2)
Requires-Dist: scipy (>=0.13.3)
Requires-Dist: six (>=1.9.0)
Requires-Dist: wget (==2.0)
Requires-Dist: xmltodict (==0.8.6)
